<annotation>
	<folder>My Photos</folder>
	<filename>20180608_213423(0).jpg</filename>
	<path>C:\Users\Nico Angelo\Desktop\thesis\dataset\self-acquired\My Photos\20180608_213423(0).jpg</path>
	<source>
		<database>Unknown</database>
	</source>
	<size>
		<width>2560</width>
		<height>1440</height>
		<depth>3</depth>
	</size>
	<segmented>0</segmented>
	<object>
		<name>facewithglasses</name>
		<pose>Unspecified</pose>
		<truncated>0</truncated>
		<difficult>0</difficult>
		<bndbox>
			<xmin>164</xmin>
			<ymin>410</ymin>
			<xmax>883</xmax>
			<ymax>1097</ymax>
		</bndbox>
	</object>
	<object>
		<name>facewithglasses</name>
		<pose>Unspecified</pose>
		<truncated>0</truncated>
		<difficult>0</difficult>
		<bndbox>
			<xmin>1064</xmin>
			<ymin>435</ymin>
			<xmax>1570</xmax>
			<ymax>910</ymax>
		</bndbox>
	</object>
</annotation>
