<annotation>
	<folder>Trixia Belleza's FB photos</folder>
	<filename>33662374_1903664616313022_863215394872098816_n.jpg</filename>
	<path>C:\Users\Nico Angelo\Desktop\thesis\dataset\self-acquired\Trixia Belleza's FB photos\33662374_1903664616313022_863215394872098816_n.jpg</path>
	<source>
		<database>Unknown</database>
	</source>
	<size>
		<width>960</width>
		<height>720</height>
		<depth>3</depth>
	</size>
	<segmented>0</segmented>
	<object>
		<name>facewithglasses</name>
		<pose>Unspecified</pose>
		<truncated>0</truncated>
		<difficult>0</difficult>
		<bndbox>
			<xmin>553</xmin>
			<ymin>172</ymin>
			<xmax>639</xmax>
			<ymax>267</ymax>
		</bndbox>
	</object>
	<object>
		<name>facewithglasses</name>
		<pose>Unspecified</pose>
		<truncated>0</truncated>
		<difficult>0</difficult>
		<bndbox>
			<xmin>474</xmin>
			<ymin>189</ymin>
			<xmax>534</xmax>
			<ymax>261</ymax>
		</bndbox>
	</object>
	<object>
		<name>facewithglasses</name>
		<pose>Unspecified</pose>
		<truncated>0</truncated>
		<difficult>0</difficult>
		<bndbox>
			<xmin>269</xmin>
			<ymin>158</ymin>
			<xmax>315</xmax>
			<ymax>210</ymax>
		</bndbox>
	</object>
	<object>
		<name>facewithglasses</name>
		<pose>Unspecified</pose>
		<truncated>0</truncated>
		<difficult>0</difficult>
		<bndbox>
			<xmin>326</xmin>
			<ymin>155</ymin>
			<xmax>382</xmax>
			<ymax>228</ymax>
		</bndbox>
	</object>
	<object>
		<name>facewithglasses</name>
		<pose>Unspecified</pose>
		<truncated>0</truncated>
		<difficult>0</difficult>
		<bndbox>
			<xmin>337</xmin>
			<ymin>237</ymin>
			<xmax>402</xmax>
			<ymax>315</ymax>
		</bndbox>
	</object>
</annotation>
