<annotation>
	<folder>Remillee Pamulaklakin FB Photos</folder>
	<filename>47010299_10213242646282973_2219677186342780928_n.jpg</filename>
	<path>C:\Users\Nico Angelo\Desktop\thesis\dataset\self-acquired\Remillee Pamulaklakin FB Photos\47010299_10213242646282973_2219677186342780928_n.jpg</path>
	<source>
		<database>Unknown</database>
	</source>
	<size>
		<width>960</width>
		<height>719</height>
		<depth>3</depth>
	</size>
	<segmented>0</segmented>
	<object>
		<name>facewithglasses</name>
		<pose>Unspecified</pose>
		<truncated>0</truncated>
		<difficult>0</difficult>
		<bndbox>
			<xmin>283</xmin>
			<ymin>172</ymin>
			<xmax>422</xmax>
			<ymax>335</ymax>
		</bndbox>
	</object>
	<object>
		<name>facewithglasses</name>
		<pose>Unspecified</pose>
		<truncated>0</truncated>
		<difficult>0</difficult>
		<bndbox>
			<xmin>425</xmin>
			<ymin>123</ymin>
			<xmax>590</xmax>
			<ymax>314</ymax>
		</bndbox>
	</object>
</annotation>
